isqlab/__init__.py
isqlab/backend/__init__.py
isqlab/backend/abstract_backend.py
isqlab/backend/autograd_backend.py
isqlab/backend/jax_backend.py
isqlab/backend/numpy_sim_backend.py
isqlab/backend/torch_backend.py
isqlab/circuits/__init__.py
isqlab/circuits/isq_circuit.py
isqlab/circuits/quantum_circuit.py
isqlab/linkers/__init__.py
isqlab/linkers/torch_layer.py
isqlab/linkers/torch_linker.py
isqlab/neural_networks/__init__.py
isqlab/neural_networks/neural_network.py
isqlab/neural_networks/qnn_autograd.py
isqlab/neural_networks/qnn_jax.py
isqlab/neural_networks/qnn_simulator.py
isqlab/vqe/__init__.py
isqlab/vqe/chem.py
isqlab/vqe/hamiltonian_measure.py
isqlab/vqe/kupccgsd.py
isqlab/vqe/symmetry_preserving.py
isqlab/vqe/ucc.py
isqlab/vqe/uccsd.py
isqlab-0.3.9.dist-info/LICENSE
isqlab-0.3.9.dist-info/METADATA
isqlab-0.3.9.dist-info/WHEEL
isqlab-0.3.9.dist-info/top_level.txt
isqlab-0.3.9.dist-info/RECORD
