Metadata-Version: 2.1
Name: isqlab
Version: 0.3.9
Summary: application modules for isq
Author: Yusheng Yang
Author-email: yangys@arclightquantum.com
License: MIT
Platform: python 3.8+
Requires-Python: >=3.8
License-File: LICENSE
Requires-Dist: isqopen
